{"train_no": "247", "has_breastfeeding_rooms": true, "carries_packages": false, "has_dining_rooms": false, "is_accessible": true, "has_bike_stands": false, "train_class": "1107", "stops": [{"station": "7000", "departs_at": "20:30", "arrives_at": "20:28"}, {"station": "7160", "departs_at": "21:22", "arrives_at": "21:20"}, {"station": "7190", "departs_at": "21:30", "arrives_at": "21:28"}, {"station": "7210", "departs_at": "21:37", "arrives_at": "21:36"}, {"station": "7230", "departs_at": "21:43", "arrives_at": "21:42"}, {"station": "0990", "departs_at": "22:36", "arrives_at": "22:35"}, {"station": "1000", "departs_at": "22:47", "arrives_at": "22:43"}, {"station": "1020", "departs_at": "22:56", "arrives_at": "22:54"}, {"station": "1040", "departs_at": "23:05", "arrives_at": "23:02"}]}